IRTSD/__init__.py
IRTSD/environment.py
IRTSD/callbacks/__init__.py
IRTSD/callbacks/trainer.py
IRTSD/datasets/__init__.py
IRTSD/datasets/datasets.py
IRTSD/models/IRSTDNet.py
IRTSD/models/MLPNet_network.py
IRTSD/models/SCTransNet.py
IRTSD/models/__init__.py
IRTSD/models/mim_network.py
IRTSD/tools/__init__.py
IRTSD/tools/loss.py
IRTSD/tools/metrics.py
IRTSD/tools/utils.py
IRSTD-0.0.0.1.dist-info/METADATA
IRSTD-0.0.0.1.dist-info/WHEEL
IRSTD-0.0.0.1.dist-info/top_level.txt
IRSTD-0.0.0.1.dist-info/zip-safe
IRSTD-0.0.0.1.dist-info/RECORD
