Metadata-Version: 2.2
Name: IRSTD
Version: 0.0.0.1
Summary: It is a DeepLearning package to foster developed by Aohua Li
Home-page: https://github.com/PepperCS/IRSTD
Author: Aohua Li
Author-email: liah24@mails.jlu.edu.cn
Requires-Python: >=3.7
Dynamic: author
Dynamic: author-email
Dynamic: description
Dynamic: description-content-type
Dynamic: home-page
Dynamic: requires-python
Dynamic: summary
